mxmul_pkg_wht/__init__.py
mxmul_pkg_wht/mxmul.py
mxmul_pkg_wht-0.1.0.dist-info/LICENSE
mxmul_pkg_wht-0.1.0.dist-info/METADATA
mxmul_pkg_wht-0.1.0.dist-info/WHEEL
mxmul_pkg_wht-0.1.0.dist-info/top_level.txt
mxmul_pkg_wht-0.1.0.dist-info/RECORD
